quantuloop_simulator/__init__.py
quantuloop_simulator-2023.3b1.dist-info/LICENSE
quantuloop_simulator-2023.3b1.dist-info/METADATA
quantuloop_simulator-2023.3b1.dist-info/WHEEL
quantuloop_simulator-2023.3b1.dist-info/RECORD
