Metadata-Version: 2.1
Name: quantuloop-simulator
Version: 2023.3b1
Summary: Quantuloop Quantum Simulator Suite for HPC
Author: Quantuloop
Author-email: dev@quantuloop.com
Requires-Python: >=3.7,<4.0
Classifier: Programming Language :: Python :: 3
Classifier: Programming Language :: Python :: 3.7
Classifier: Programming Language :: Python :: 3.8
Classifier: Programming Language :: Python :: 3.9
Classifier: Programming Language :: Python :: 3.10
Classifier: Programming Language :: Python :: 3.11
Requires-Dist: quantuloop-dense (>=0.2.0.rc1,<0.3.0)
Requires-Dist: quantuloop-quest (>=0.2.0.rc1,<0.3.0)
Requires-Dist: quantuloop-sparse (>=0.2.0.rc1,<0.3.0)
